[{"X": 0, "ST": 3, "STN": null, "ID": "``49084", "SN": "`she is`", "EN": "Ghost in the Shell: Stand Alone Complex 2nd GIG", "SA": "Gabriela Robin", "AID": 8495, "animeRomajiName": "Koukaku Kidoutai S.A.C. 2nd GIG", "animeEnglishName": "Ghost in the Shell: Stand Alone Complex 2nd GIG", "altAnimeNames": ["Koukaku Kidoutai S.A.C. 2nd GIG", "Ghost in the Shell: Stand Alone Complex 2nd GIG"], "altAnimeNamesAnswers": [], "songArtist": "Gabriela Robin", "artistInfo": {"name": "Yoko Kanno", "memberArtists": [], "memberGroups": [], "memberInGroups": [], "altNames": [], "artistId": 21}, "songArranger": "Yoko Kanno", "arrangerInfo": {"name": "Yoko Kanno", "memberArtists": [], "memberGroups": [], "memberInGroups": [], "altNames": [], "artistId": 21}, "songComposer": "Yoko Kanno", "composerInfo": {"name": "Yoko Kanno", "memberArtists": [], "memberGroups": [], "memberInGroups": [], "altNames": [], "artistId": 21}, "songName": "she is", "songType": 3, "songTypeNumber": null, "songDifficulty": 17, "animeType": "TV", "animeVintage": "Winter 2004", "annId": 49084, "malId": 801, "kitsuId": 715, "aniListId": 801, "animeTags": [], "animeGenre": [], "rebroadcast": false, "dub": false, "startPoint": null, "annSongId": 49084, "length": 147.458, "audio": "n56b1w.mp3", "video480": "", "video720": "wl03j4ujidn1rpzn.webm", "correctGuess": null, "incorrectGuess": null, "CountDown": 2147489783, "sampleWeights": [0, 0, 0, 0, 0, 0, 0, 0, 0, 0, 0, 0, 0, 0, 0, 0, 0, 0, 0, 0], "D": 0}
,{"X": 0, "ST": 2, "STN": 1, "ID": "``47300", "SN": "`Aka to Ao`", "EN": "Kaguya-sama: Love is War - The Stairs to Adulthood", "SA": "Aoi Koga", "AID": 36700, "animeRomajiName": "Kaguya-sama wa Kokurasetai: Otona e no Kaidan", "animeEnglishName": "Kaguya-sama: Love is War - The Stairs to Adulthood", "altAnimeNames": ["Kaguya-sama wa Kokurasetai: Otona e no Kaidan", "Kaguya-sama: Love is War - The Stairs to Adulthood"], "altAnimeNamesAnswers": [], "songArtist": "Aoi Koga", "artistInfo": {"name": "Aoi Koga", "memberArtists": [], "memberGroups": [], "memberInGroups": [], "altNames": [], "artistId": 6957}, "songArranger": "", "arrangerInfo": null, "songComposer": "Tsubasa Itou & Yuki Tsujimura", "composerInfo": {"name": "Yuki Tsujimura", "memberArtists": [], "memberGroups": [], "memberInGroups": [], "altNames": [], "artistId": 7007}, "songName": "Aka to Ao", "songType": 2, "songTypeNumber": 1, "songDifficulty": 25, "animeType": "Special", "animeVintage": "Fall 2025", "annId": 47300, "malId": 61903, "kitsuId": 49998, "aniListId": 194884, "animeTags": [], "animeGenre": [], "rebroadcast": false, "dub": false, "startPoint": null, "annSongId": 47300, "length": 91.765, "audio": "4oap9g.mp3", "video480": "", "video720": "fv4b91b0r7omcdph.webm", "correctGuess": null, "incorrectGuess": null, "CountDown": 2147489560, "sampleWeights": [0, 0, 0, 0, 0, 0, 0, 0, 0, 0, 0, 0, 0], "D": 0}
]