[{"X": 0, "ST": 2, "STN": 2, "ID": "``14857", "SN": "`Saigo made II`", "EN": "Gintama\u00b0", "SA": "Aqua Timez", "AID": 16644, "animeRomajiName": "Gintama\u00b0", "animeEnglishName": "Gintama\u00b0", "altAnimeNames": ["Gintama\u00b0", "Gintama\u00b0"], "altAnimeNamesAnswers": [], "songArtist": "Aqua Timez", "songArranger": "akkin & Aqua Timez", "songComposer": "Futoshi", "songName": "Saigo made II", "songType": 2, "songTypeNumber": 2, "songDifficulty": 20, "animeType": "TV", "animeVintage": "Spring 2015", "annId": 14857, "malId": 28977, "kitsuId": 10083, "aniListId": 20996, "animeTags": [], "animeGenre": [], "rebroadcast": false, "dub": false, "startPoint": 0, "annSongId": 14857, "length": 89.016, "audio": "k6u8y8.mp3", "video480": "72omk1.webm", "video720": "pwicn2.webm", "correctGuess": null, "incorrectGuess": null, "sampleWeights": [0, 1, 0, 0, 0, 0, 1, 0, 1, 0, 0, 0], "D": 0.0}, {"X": 0, "ST": 3, "STN": null, "ID": "``45357", "SN": "`Beginning`", "EN": "Mobile Suit Gundam GQuuuuuuX", "SA": "Daisuke Inoue", "AID": 34125, "animeRomajiName": "Kidou Senshi Gundam GQuuuuuuX", "animeEnglishName": "Mobile Suit Gundam GQuuuuuuX", "altAnimeNames": ["Kidou Senshi Gundam GQuuuuuuX", "Mobile Suit Gundam GQuuuuuuX"], "altAnimeNamesAnswers": ["Kidou Senshi Gundam Movie Trilogy", "Mobile Suit Gundam: The Movie Trilogy", "Gundam vs. Hello Kitty"], "songArtist": "Daisuke Inoue", "songArranger": "Daisuke Inoue", "songComposer": "Daisuke Inoue", "songName": "Beginning", "songType": 3, "songTypeNumber": null, "songDifficulty": 38, "animeType": "TV", "animeVintage": "Spring 2025", "annId": 45357, "malId": 60449, "kitsuId": null, "aniListId": 185213, "animeTags": [], "animeGenre": [], "rebroadcast": false, "dub": false, "startPoint": 80.25129383018066, "annSongId": 45357, "length": 138.242, "audio": "v3f3rj8dz4bx11sp.mp3", "video480": "", "video720": "cxevtc0dr42xh3kw.webm", "correctGuess": null, "incorrectGuess": null, "sampleWeights": [1, 0, 1, 0, 0, 1, 1, 1, 0, 1, 0, 2, 0, 0, 0, 1, 1, 1, 0], "D": 6.6578554729371024}, {"X": 0, "ST": 3, "STN": null, "ID": "``44776", "SN": "`Miraijima ~Future Island~`", "EN": "One Piece", "SA": "Mori Calliope", "AID": 836, "animeRomajiName": "One Piece", "animeEnglishName": "One Piece", "altAnimeNames": ["One Piece", "One Piece"], "altAnimeNamesAnswers": [], "songArtist": "Mori Calliope", "songArranger": "Hidefumi Kenmochi", "songComposer": "Hidefumi Kenmochi", "songName": "Miraijima ~Future Island~", "songType": 3, "songTypeNumber": null, "songDifficulty": 30, "animeType": "TV", "animeVintage": "Fall 1999", "annId": 44776, "malId": 21, "kitsuId": 12, "aniListId": 21, "animeTags": [], "animeGenre": [], "rebroadcast": false, "dub": false, "startPoint": 65.36569930033653, "annSongId": 44776, "length": 89.214, "audio": "wz036y.mp3", "video480": "hyuoae.webm", "video720": "v2bwfq.webm", "correctGuess": null, "incorrectGuess": null, "sampleWeights": [0, 2, 0, 0, 1, 2, 0, 0, 1, 1, 1, 2], "D": 6.80277542266378}, {"X": 0, "ST": 3, "STN": null, "ID": "``33784", "SN": "`Bucchakete For You`", "EN": "Zombie Land Saga Revenge", "SA": "FranChouChou", "AID": 24019, "animeRomajiName": "Zombie Land Saga Revenge", "animeEnglishName": "Zombie Land Saga Revenge", "altAnimeNames": ["Zombie Land Saga Revenge", "Zombie Land Saga Revenge"], "altAnimeNamesAnswers": [], "songArtist": "FranChouChou", "songArranger": "Tomoya Kawasaki", "songComposer": "Tomoya Kawasaki", "songName": "Bucchakete For You", "songType": 3, "songTypeNumber": null, "songDifficulty": 22, "animeType": "TV", "animeVintage": "Spring 2021", "annId": 33784, "malId": 40174, "kitsuId": 42467, "aniListId": 110733, "animeTags": [], "animeGenre": [], "rebroadcast": false, "dub": false, "startPoint": 7.35044966022455, "annSongId": 33784, "length": 118.68, "audio": "3o3ypf.mp3", "video480": "19whqc.webm", "video720": "0vdhhq.webm", "correctGuess": null, "incorrectGuess": null, "sampleWeights": [1, 1, 0, 0, 1, 1, 0, 0, 0, 1, 0, 1, 1, 0, 0, 0], "D": 3.3265063108771393}, {"X": 0, "ST": 1, "STN": 2, "ID": "``11759", "SN": "`My Dearest`", "EN": "Guilty Crown", "SA": "supercell", "AID": 13001, "animeRomajiName": "Guilty Crown", "animeEnglishName": "Guilty Crown", "altAnimeNames": ["Guilty Crown", "Guilty Crown"], "altAnimeNamesAnswers": [], "songArtist": "supercell", "songArranger": "ryo", "songComposer": "ryo", "songName": "My Dearest", "songType": 1, "songTypeNumber": 2, "songDifficulty": 73, "animeType": "TV", "animeVintage": "Fall 2011", "annId": 11759, "malId": 10793, "kitsuId": 6349, "aniListId": 10793, "animeTags": [], "animeGenre": [], "rebroadcast": false, "dub": false, "startPoint": 0, "annSongId": 11759, "length": 90.024, "audio": "w0mytn.mp3", "video480": "7g86wu.webm", "video720": "mv5kou.webm", "correctGuess": null, "incorrectGuess": null, "sampleWeights": [0, 0, 0, 0, 0, 1, 0, 0, 0, 0, 0, 0, 0], "D": 1.0}, {"X": 0, "ST": 3, "STN": null, "ID": "``23929", "SN": "`Monochrome`", "EN": "Domestic Girlfriend", "SA": "Maaya Uchida", "AID": 21205, "animeRomajiName": "Domestic na Kanojo", "animeEnglishName": "Domestic Girlfriend", "altAnimeNames": ["Domestic na Kanojo", "Domestic Girlfriend"], "altAnimeNamesAnswers": [], "songArtist": "Maaya Uchida", "songArranger": "Naoki Itou", "songComposer": "Naoki Itou", "songName": "Monochrome", "songType": 3, "songTypeNumber": null, "songDifficulty": 18, "animeType": "TV", "animeVintage": "Winter 2019", "annId": 23929, "malId": 37982, "kitsuId": 41479, "aniListId": 103139, "animeTags": [], "animeGenre": [], "rebroadcast": false, "dub": false, "startPoint": 84.17854982069028, "annSongId": 23929, "length": 115.896, "audio": "q796sa.mp3", "video480": "", "video720": "wuae4l.webm", "correctGuess": null, "incorrectGuess": null, "sampleWeights": [0, 1, 0, 0, 0, 0, 0, 0, 0, 0, 0, 0, 0, 0, 0, 0], "D": 1.0}, {"X": 0, "ST": 3, "STN": null, "ID": "``41889", "SN": "`Garden`", "EN": "Spy \u00d7 Family", "SA": "(K)NoW_NAME:NIKIIE", "AID": 26746, "animeRomajiName": "Spy \u00d7 Family", "animeEnglishName": "Spy \u00d7 Family", "altAnimeNames": ["Spy \u00d7 Family", "Spy \u00d7 Family"], "altAnimeNamesAnswers": [], "songArtist": "(K)NoW_NAME:NIKIIE", "songArranger": "(K)NoW_NAME:Makoto Miyazaki", "songComposer": "(K)NoW_NAME:Makoto Miyazaki", "songName": "Garden", "songType": 3, "songTypeNumber": null, "songDifficulty": 26, "animeType": "TV", "animeVintage": "Fall 2023", "annId": 41889, "malId": 53887, "kitsuId": 46873, "aniListId": 158927, "animeTags": [], "animeGenre": [], "rebroadcast": false, "dub": false, "startPoint": 8.857963200706054, "annSongId": 41889, "length": 149.016, "audio": "kld6wx.mp3", "video480": "", "video720": "2fv70p.webm", "correctGuess": null, "incorrectGuess": null, "sampleWeights": [0, 0, 0, 1, 0, 0, 0, 0, 0, 0, 0, 0, 0, 1, 0, 0, 0, 0, 0, 0], "D": 4.922993362430228}, {"X": 0, "ST": 2, "STN": 3, "ID": "``11399", "SN": "`Tsunagaru made`", "EN": "Sacred Seven", "SA": "Megumi Nakajima", "AID": 12393, "animeRomajiName": "Sacred Seven", "animeEnglishName": "Sacred Seven", "altAnimeNames": ["Sacred Seven", "Sacred Seven"], "altAnimeNamesAnswers": [], "songArtist": "Megumi Nakajima", "songArranger": "Dan Miyakawa", "songComposer": "Dan Miyakawa", "songName": "Tsunagaru made", "songType": 2, "songTypeNumber": 3, "songDifficulty": 19, "animeType": "TV", "animeVintage": "Summer 2011", "annId": 11399, "malId": 10156, "kitsuId": 6058, "aniListId": 10156, "animeTags": [], "animeGenre": [], "rebroadcast": false, "dub": false, "startPoint": 33.059668058107064, "annSongId": 11399, "length": 164.76, "audio": "xup1bu.mp3", "video480": "", "video720": "ifucyj.webm", "correctGuess": null, "incorrectGuess": null, "sampleWeights": [0, 0, 1, 1, 0, 0, 0, 1, 0, 0, 0, 0, 0, 0, 0, 0, 0, 0, 0, 1, 0, 0], "D": 0.0}, {"X": 0, "ST": 2, "STN": 1, "ID": "``46463", "SN": "`Arifuretetai`", "EN": "Alma-chan Wants to Have a Family!", "SA": "KAF", "AID": 34354, "animeRomajiName": "Alma-chan wa Kazoku ni Naritai", "animeEnglishName": "Alma-chan Wants to Have a Family!", "altAnimeNames": ["Alma-chan wa Kazoku ni Naritai", "Alma-chan Wants to Have a Family!"], "altAnimeNamesAnswers": [], "songArtist": "KAF", "songArranger": "Junichi Matsuda", "songComposer": "Junichi Matsuda & MILKEY", "songName": "Arifuretetai", "songType": 2, "songTypeNumber": 1, "songDifficulty": 32, "animeType": "TV", "animeVintage": "Fall 2025", "annId": 46463, "malId": 60781, "kitsuId": 50194, "aniListId": 186190, "animeTags": [], "animeGenre": [], "rebroadcast": false, "dub": false, "startPoint": 2.078569864670934, "annSongId": 46463, "length": 89.294, "audio": "", "video480": "", "video720": "rlts21nhl4jfkj02.webm", "correctGuess": null, "incorrectGuess": null, "sampleWeights": [0, 1, 0, 1, 0, 0, 0, 0, 1, 1, 0, 1], "D": 2.0}, {"X": 0, "ST": 3, "STN": null, "ID": "``9551", "SN": "`Sakura Jokyoku`", "EN": "Clannad After Story", "SA": "riya", "AID": 1000014, "animeRomajiName": "Clannad After Story", "animeEnglishName": "Clannad After Story", "altAnimeNames": ["Clannad After Story", "Clannad After Story"], "altAnimeNamesAnswers": [], "songArtist": "riya", "songArranger": "Hideki Higuchi", "songComposer": "Hideki Higuchi", "songName": "Sakura Jokyoku", "songType": 3, "songTypeNumber": null, "songDifficulty": 26, "animeType": "OVA", "animeVintage": "Summer 2009", "annId": 9551, "malId": 6351, "kitsuId": 4529, "aniListId": 6351, "animeTags": [], "animeGenre": [], "rebroadcast": false, "dub": false, "startPoint": 96.63432674219375, "annSongId": 9551, "length": 73.039, "audio": "9v08ii.mp3", "video480": "", "video720": "amh16e.webm", "correctGuess": null, "incorrectGuess": null, "sampleWeights": [1, 2, 1, 1, 1, 1, 1, 2, 1, 1], "D": 4.937111338711857}, {"X": 0, "ST": 3, "STN": null, "ID": "``42665", "SN": "`4eVR`", "EN": "Solo Leveling", "SA": "Benjamin & mpi, Laco", "AID": 26000, "animeRomajiName": "Ore dake Level Up na Ken", "animeEnglishName": "Solo Leveling", "altAnimeNames": ["Ore dake Level Up na Ken", "Solo Leveling"], "altAnimeNamesAnswers": [], "songArtist": "Benjamin & mpi, Laco", "songArranger": "Hiroyuki Sawano", "songComposer": "Hiroyuki Sawano", "songName": "4eVR", "songType": 3, "songTypeNumber": null, "songDifficulty": 37, "animeType": "TV", "animeVintage": "Winter 2024", "annId": 42665, "malId": 52299, "kitsuId": 46231, "aniListId": 151807, "animeTags": [], "animeGenre": [], "rebroadcast": false, "dub": false, "startPoint": 26.066698876252502, "annSongId": 42665, "length": 115.587, "audio": "7mger7.mp3", "video480": "", "video720": "0xd17s.webm", "correctGuess": null, "incorrectGuess": null, "sampleWeights": [0, 0, 0, 0, 0, 0, 0, 0, 0, 1, 0, 0, 0, 0, 0, 0], "D": 3.8974636265030362}, {"X": 0, "ST": 2, "STN": 2, "ID": "``23684", "SN": "`Always`", "EN": "Domestic Girlfriend", "SA": "Alisa Takigawa", "AID": 21205, "animeRomajiName": "Domestic na Kanojo", "animeEnglishName": "Domestic Girlfriend", "altAnimeNames": ["Domestic na Kanojo", "Domestic Girlfriend"], "altAnimeNamesAnswers": [], "songArtist": "Alisa Takigawa", "songArranger": "Ryosuke Shigenaga", "songComposer": "Alisa Takigawa", "songName": "Always", "songType": 2, "songTypeNumber": 2, "songDifficulty": 19, "animeType": "TV", "animeVintage": "Winter 2019", "annId": 23684, "malId": 37982, "kitsuId": 41479, "aniListId": 103139, "animeTags": [], "animeGenre": [], "rebroadcast": false, "dub": false, "startPoint": 92.41357571249465, "annSongId": 23684, "length": 157.776, "audio": "huqipi.mp3", "video480": "", "video720": "dz0kfm.webm", "correctGuess": null, "incorrectGuess": null, "sampleWeights": [1, 0, 0, 0, 1, 0, 0, 1, 1, 1, 1, 0, 2, 2, 1, 3, 1, 1, 0, 0, 2, 2], "D": 2.0}, {"X": 0, "ST": 3, "STN": null, "ID": "``28154", "SN": "`Time To Make History`", "EN": "Persona 4 the Golden Animation", "SA": "Shihoko Hirata", "AID": 16027, "animeRomajiName": "Persona 4 the Golden Animation", "animeEnglishName": "Persona 4 the Golden Animation", "altAnimeNames": ["Persona 4 the Golden Animation", "Persona 4 the Golden Animation"], "altAnimeNamesAnswers": [], "songArtist": "Shihoko Hirata", "songArranger": "Shouji Meguro", "songComposer": "Shouji Meguro", "songName": "Time To Make History", "songType": 3, "songTypeNumber": null, "songDifficulty": 25, "animeType": "TV", "animeVintage": "Summer 2014", "annId": 28154, "malId": 24075, "kitsuId": 8458, "aniListId": 20713, "animeTags": [], "animeGenre": [], "rebroadcast": false, "dub": false, "startPoint": 84.39317802247338, "annSongId": 28154, "length": 151.176, "audio": "q6wbdn.mp3", "video480": "", "video720": "qoopup.webm", "correctGuess": null, "incorrectGuess": null, "sampleWeights": [0, 0, 0, 1, 2, 0, 2, 0, 2, 0, 0, 0, 1, 1, 0, 0, 0, 0, 0, 0, 0], "D": 5.705912424674728}, {"X": 0, "ST": 2, "STN": 2, "ID": "``15907", "SN": "`Natsu-iro Koi Hanabi`", "EN": "Eromanga Sensei", "SA": "Akane Fujita", "AID": 18142, "animeRomajiName": "Eromanga Sensei", "animeEnglishName": "Eromanga Sensei", "altAnimeNames": ["Eromanga Sensei", "Eromanga Sensei"], "altAnimeNamesAnswers": [], "songArtist": "Akane Fujita", "songArranger": "Hiroko Yamasaki", "songComposer": "Hiroko Yamasaki", "songName": "Natsu-iro Koi Hanabi", "songType": 2, "songTypeNumber": 2, "songDifficulty": 26, "animeType": "TV", "animeVintage": "Spring 2017", "annId": 15907, "malId": 32901, "kitsuId": 11914, "aniListId": 21685, "animeTags": [], "animeGenre": [], "rebroadcast": false, "dub": false, "startPoint": 54.712932566060026, "annSongId": 15907, "length": 112.368, "audio": "viq1gx.mp3", "video480": "uq2zpo.webm", "video720": "wavx2z.webm", "correctGuess": null, "incorrectGuess": null, "sampleWeights": [1, 1, 1, 1, 1, 2, 1, 2, 1, 1, 1, 1, 1, 2, 2], "D": 2.1309558476266828}, {"X": 0, "ST": 2, "STN": 2, "ID": "``26860", "SN": "`Nounai`", "EN": "Fire Force", "SA": "Lenny code fiction", "AID": 21852, "animeRomajiName": "Enen no Shouboutai", "animeEnglishName": "Fire Force", "altAnimeNames": ["Enen no Shouboutai", "Fire Force"], "altAnimeNamesAnswers": [], "songArtist": "Lenny code fiction", "songArranger": "Lenny code fiction & akkin", "songComposer": "Ko Katagiri", "songName": "Nounai", "songType": 2, "songTypeNumber": 2, "songDifficulty": 32, "animeType": "TV", "animeVintage": "Summer 2019", "annId": 26860, "malId": 38671, "kitsuId": 42068, "aniListId": 105310, "animeTags": [], "animeGenre": [], "rebroadcast": false, "dub": false, "startPoint": 66.14491788684958, "annSongId": 26860, "length": 89.04, "audio": "w1tzd4.mp3", "video480": "rsqlpd.webm", "video720": "hkt7ei.webm", "correctGuess": null, "incorrectGuess": null, "sampleWeights": [1, 0, 0, 0, 0, 0, 0, 0, 1, 0, 0, 0], "D": 1.0}, {"X": 0, "ST": 2, "STN": 3, "ID": "``43627", "SN": "`Night Diver`", "EN": "Mayonaka Punch", "SA": "Fairouz Ai, Yuina Ito, Hina Youmiya, Hitomi Ueda", "AID": 31813, "animeRomajiName": "Mayonaka Punch", "animeEnglishName": "Mayonaka Punch", "altAnimeNames": ["Mayonaka Punch", "Mayonaka Punch"], "altAnimeNamesAnswers": [], "songArtist": "Fairouz Ai, Yuina Ito, Hina Youmiya, Hitomi Ueda", "songArranger": "raku", "songComposer": "raku", "songName": "Night Diver", "songType": 2, "songTypeNumber": 3, "songDifficulty": 28, "animeType": "TV", "animeVintage": "Summer 2024", "annId": 43627, "malId": 57947, "kitsuId": 48467, "aniListId": 174044, "animeTags": [], "animeGenre": [], "rebroadcast": false, "dub": false, "startPoint": 0, "annSongId": 43627, "length": 177.892, "audio": "8h70tt.mp3", "video480": "", "video720": "yv60ao.webm", "correctGuess": null, "incorrectGuess": null, "sampleWeights": [0, 0, 0, 0, 0, 0, 0, 0, 0, 0, 0, 1, 0, 0, 0, 0, 0, 0, 0, 0, 1, 0, 0, 0], "D": 8}, {"X": 0, "ST": 2, "STN": 1, "ID": "``16347", "SN": "`SILVER`", "EN": "Gintama.", "SA": "RIZE", "AID": 18901, "animeRomajiName": "Gintama.", "animeEnglishName": "Gintama.", "altAnimeNames": ["Gintama.", "Gintama."], "altAnimeNamesAnswers": [], "songArtist": "RIZE", "songArranger": "RIZE", "songComposer": "KenKen", "songName": "SILVER", "songType": 2, "songTypeNumber": 1, "songDifficulty": 23, "animeType": "TV", "animeVintage": "Winter 2017", "annId": 16347, "malId": 34096, "kitsuId": 12553, "aniListId": 97889, "animeTags": [], "animeGenre": [], "rebroadcast": false, "dub": false, "startPoint": 4.589397399527972, "annSongId": 16347, "length": 88.824, "audio": "sr7uic.mp3", "video480": "", "video720": "zitys9.webm", "correctGuess": null, "incorrectGuess": null, "sampleWeights": [2, 2, 3, 3, 2, 2, 2, 0, 1, 3, 2, 2], "D": 2.239250909421835}, {"X": 0, "ST": 3, "STN": null, "ID": "``12589", "SN": "`Hajimari no Tane`", "EN": "Love, Chunibyo & Other Delusions!", "SA": "ZAQ", "AID": 14448, "animeRomajiName": "Chu-2 Byou demo Koi ga Shitai!", "animeEnglishName": "Love, Chunibyo & Other Delusions!", "altAnimeNames": ["Chu-2 Byou demo Koi ga Shitai!", "Love, Chunibyo & Other Delusions!", "Chuunibyou demo Koi ga Shitai!"], "altAnimeNamesAnswers": [], "songArtist": "ZAQ", "songArranger": "ZAQ", "songComposer": "ZAQ", "songName": "Hajimari no Tane", "songType": 3, "songTypeNumber": null, "songDifficulty": 25, "animeType": "TV", "animeVintage": "Fall 2012", "annId": 12589, "malId": 14741, "kitsuId": 7160, "aniListId": 14741, "animeTags": [], "animeGenre": [], "rebroadcast": false, "dub": false, "startPoint": 46.11073239243742, "annSongId": 12589, "length": 119.667, "audio": "jbhyya.mp3", "video480": "", "video720": "xjbjak.webm", "correctGuess": null, "incorrectGuess": null, "sampleWeights": [0, 0, 0, 1, 0, 1, 1, 0, 1, 1, 0, 0, 0, 0, 1, 1], "D": 1.2679491924311228}, {"X": 0, "ST": 1, "STN": 1, "ID": "``11411", "SN": "`Matryoshka`", "EN": "C: Control", "SA": "NICO Touches the Walls", "AID": 12400, "animeRomajiName": "C: The Money of Soul and Possibility - Control", "animeEnglishName": "C: Control", "altAnimeNames": ["C: The Money of Soul and Possibility - Control", "C: Control"], "altAnimeNamesAnswers": [], "songArtist": "NICO Touches the Walls", "songArranger": "NICO Touches the Walls & Junji Ishiwatari", "songComposer": "Shingo Sakakura", "songName": "Matryoshka", "songType": 1, "songTypeNumber": 1, "songDifficulty": 36, "animeType": "TV", "animeVintage": "Spring 2011", "annId": 11411, "malId": 10163, "kitsuId": 6061, "aniListId": 10163, "animeTags": [], "animeGenre": [], "rebroadcast": false, "dub": false, "startPoint": 40.31499182612241, "annSongId": 11411, "length": 88.416, "audio": "tqtrvv.mp3", "video480": "", "video720": "1mncxg.webm", "correctGuess": null, "incorrectGuess": null, "sampleWeights": [0, 0, 1, 1, 2, 0, 1, 0, 1, 2, 0, 0], "D": 2.9160003713815073}, {"X": 0, "ST": 3, "STN": null, "ID": "``28046", "SN": "`Kimi 100% Jinsei`", "EN": "PriPara", "SA": "Nozomi Yamamoto", "AID": 16674, "animeRomajiName": "PriPara", "animeEnglishName": "PriPara", "altAnimeNames": ["PriPara", "PriPara"], "altAnimeNamesAnswers": ["Gekijouban PriPara: Mi~nna Atsumare! Prism\u2606Tours"], "songArtist": "Nozomi Yamamoto", "songArranger": "Kazuhiro Yamahara", "songComposer": "Kazuhiro Yamahara", "songName": "Kimi 100% Jinsei", "songType": 3, "songTypeNumber": null, "songDifficulty": 23, "animeType": "TV", "animeVintage": "Spring 2015", "annId": 28046, "malId": 23135, "kitsuId": 8555, "aniListId": 20742, "animeTags": [], "animeGenre": [], "rebroadcast": false, "dub": false, "startPoint": 63.06652602777365, "annSongId": 28046, "length": 26.04, "audio": "68b4b8.mp3", "video480": "", "video720": "h2mt2i.webm", "correctGuess": null, "incorrectGuess": null, "sampleWeights": [1, 1, 0, 2], "D": 6.311287177218427}, {"X": 0, "ST": 3, "STN": null, "ID": "``32164", "SN": "`Brand New World`", "EN": "D4DJ First Mix", "SA": "Happy Around!", "AID": 23530, "animeRomajiName": "D4DJ First Mix", "animeEnglishName": "D4DJ First Mix", "altAnimeNames": ["D4DJ First Mix", "D4DJ First Mix"], "altAnimeNamesAnswers": [], "songArtist": "Happy Around!", "songArranger": "fu_mou", "songComposer": "fu_mou", "songName": "Brand New World", "songType": 3, "songTypeNumber": null, "songDifficulty": 26, "animeType": "TV", "animeVintage": "Fall 2020", "annId": 32164, "malId": 39681, "kitsuId": 43557, "aniListId": 115069, "animeTags": [], "animeGenre": [], "rebroadcast": false, "dub": false, "startPoint": 5.168913722902872, "annSongId": 32164, "length": 109.968, "audio": "v3shzl.mp3", "video480": "", "video720": "g6qayx.webm", "correctGuess": null, "incorrectGuess": null, "sampleWeights": [0, 0, 0, 0, 0, 0, 0, 0, 1, 1, 0, 1, 1, 1, 0], "D": 1.0}, {"X": 0, "ST": 1, "STN": 60, "ID": "``45817", "SN": "`Poker Face`", "EN": "Detective Conan", "SA": "amyuri", "AID": 454, "animeRomajiName": "Meitantei Conan", "animeEnglishName": "Detective Conan", "altAnimeNames": ["Meitantei Conan", "Detective Conan", "Case Closed"], "altAnimeNamesAnswers": [], "songArtist": "amyuri", "songArranger": "amyuri", "songComposer": "amyuri", "songName": "Poker Face", "songType": 1, "songTypeNumber": 60, "songDifficulty": 17, "animeType": "TV", "animeVintage": "Winter 1996", "annId": 45817, "malId": 235, "kitsuId": 210, "aniListId": 235, "animeTags": [], "animeGenre": [], "rebroadcast": false, "dub": false, "startPoint": 64.04124424536981, "annSongId": 45817, "length": 113.545, "audio": "fryoa9.mp3", "video480": "", "video720": "uyihqjs1mzi8xnlp.webm", "correctGuess": null, "incorrectGuess": null, "sampleWeights": [0, 1, 0, 0, 0, 0, 0, 2, 0, 0, 1, 0, 0, 0, 0, 0], "D": 4.0}, {"X": 0, "ST": 2, "STN": 1, "ID": "``9501", "SN": "`Revolution`", "EN": "The Slayers Revolution", "SA": "Megumi Hayashibara", "AID": 9500, "animeRomajiName": "Slayers Revolution", "animeEnglishName": "The Slayers Revolution", "altAnimeNames": ["Slayers Revolution", "The Slayers Revolution"], "altAnimeNamesAnswers": [], "songArtist": "Megumi Hayashibara", "songArranger": "Go Takahashi", "songComposer": "Go Takahashi", "songName": "Revolution", "songType": 2, "songTypeNumber": 1, "songDifficulty": 18, "animeType": "TV", "animeVintage": "Summer 2008", "annId": 9501, "malId": 4028, "kitsuId": 3421, "aniListId": 4028, "animeTags": [], "animeGenre": [], "rebroadcast": false, "dub": false, "startPoint": 24.189842021883972, "annSongId": 9501, "length": 88.008, "audio": "jyi2wg.mp3", "video480": "b9t3zy.webm", "video720": "", "correctGuess": null, "incorrectGuess": null, "sampleWeights": [1, 0, 0, 0, 1, 0, 0, 0, 0, 0, 1, 0], "D": 1.0}, {"X": 0, "ST": 1, "STN": 50, "ID": "``24645", "SN": "`ANSWER`", "EN": "Detective Conan", "SA": "Only this time", "AID": 454, "animeRomajiName": "Meitantei Conan", "animeEnglishName": "Detective Conan", "altAnimeNames": ["Meitantei Conan", "Detective Conan", "Case Closed"], "altAnimeNamesAnswers": [], "songArtist": "Only this time", "songArranger": "Nob from MY FIRST STORY", "songComposer": "Taisei Miyakawa", "songName": "ANSWER", "songType": 1, "songTypeNumber": 50, "songDifficulty": 24, "animeType": "TV", "animeVintage": "Winter 1996", "annId": 24645, "malId": 235, "kitsuId": 210, "aniListId": 235, "animeTags": [], "animeGenre": [], "rebroadcast": false, "dub": false, "startPoint": 92.60216573390696, "annSongId": 24645, "length": 114.048, "audio": "uppv94.mp3", "video480": "4wg4rk.webm", "video720": "b2mjtg.webm", "correctGuess": null, "incorrectGuess": null, "sampleWeights": [0, 2, 2, 2, 1, 1, 1, 0, 2, 2, 2, 3, 1, 1, 2, 1], "D": 1.9777483666761875}, {"X": 0, "ST": 3, "STN": null, "ID": "``11511", "SN": "`Hana`", "EN": "The Idol Master", "SA": "Juri Takita", "AID": 12436, "animeRomajiName": "The iDOLM@STER", "animeEnglishName": "The Idol Master", "altAnimeNames": ["The iDOLM@STER", "The Idol Master"], "altAnimeNamesAnswers": [], "songArtist": "Juri Takita", "songArranger": "Jun Kageie", "songComposer": "Miki Fujisue", "songName": "Hana", "songType": 3, "songTypeNumber": null, "songDifficulty": 13, "animeType": "TV", "animeVintage": "Summer 2011", "annId": 11511, "malId": 10278, "kitsuId": 6111, "aniListId": 10278, "animeTags": [], "animeGenre": [], "rebroadcast": false, "dub": false, "startPoint": 75.6800797097424, "annSongId": 11511, "length": 141.24, "audio": "lu9pqh.mp3", "video480": "", "video720": "qpc5df.webm", "correctGuess": null, "incorrectGuess": null, "sampleWeights": [0, 0, 0, 1, 0, 2, 0, 0, 0, 1, 0, 0, 0, 0, 1, 0, 0, 1, 0], "D": 2.0}, {"X": 0, "ST": 1, "STN": 1, "ID": "``20141", "SN": "`Everybody GO!`", "EN": "Puzzle & Dragons", "SA": "Asuna Tomari", "AID": 20881, "animeRomajiName": "PazuDora", "animeEnglishName": "Puzzle & Dragons", "altAnimeNames": ["PazuDora", "Puzzle & Dragons"], "altAnimeNamesAnswers": [], "songArtist": "Asuna Tomari", "songArranger": "Agasa.K", "songComposer": "GungHo Music Factory", "songName": "Everybody GO!", "songType": 1, "songTypeNumber": 1, "songDifficulty": 20, "animeType": "TV", "animeVintage": "Spring 2018", "annId": 20141, "malId": 37096, "kitsuId": null, "aniListId": 101424, "animeTags": [], "animeGenre": [], "rebroadcast": false, "dub": false, "startPoint": 38.25435424609621, "annSongId": 20141, "length": 87.667, "audio": "x8mqem.mp3", "video480": "", "video720": "k37i73.webm", "correctGuess": null, "incorrectGuess": null, "sampleWeights": [0, 2, 1, 0, 0, 1, 2, 0, 0, 1, 0, 1], "D": 7.916903802786768}, {"X": 0, "ST": 2, "STN": 2, "ID": "``13228", "SN": "`Expect`", "EN": "Gintama'", "SA": "PAGE", "AID": 15223, "animeRomajiName": "Gintama'", "animeEnglishName": "Gintama'", "altAnimeNames": ["Gintama'", "Gintama'", "Gintama' Enchousen"], "altAnimeNamesAnswers": [], "songArtist": "PAGE", "songArranger": "Takane Shinsaku", "songComposer": "PAGE", "songName": "Expect", "songType": 2, "songTypeNumber": 2, "songDifficulty": 21, "animeType": "TV", "animeVintage": "Fall 2012", "annId": 13228, "malId": 15417, "kitsuId": 7253, "aniListId": 15417, "animeTags": [], "animeGenre": [], "rebroadcast": false, "dub": false, "startPoint": 73.50148577521358, "annSongId": 13228, "length": 88.296, "audio": "u5b9g0.mp3", "video480": "twb90y.webm", "video720": "cz0ypt.webm", "correctGuess": null, "incorrectGuess": null, "sampleWeights": [0, 0, 0, 0, 0, 0, 1, 0, 0, 0, 0, 0], "D": 1.0}, {"X": 0, "ST": 1, "STN": 2, "ID": "``15555", "SN": "`Zettai Reido \u03b8 Novatic`", "EN": "Macross Delta", "SA": "Walk\u00fcre", "AID": 17762, "animeRomajiName": "Macross \u0394", "animeEnglishName": "Macross Delta", "altAnimeNames": ["Macross \u0394", "Macross Delta"], "altAnimeNamesAnswers": ["Gekijouban Macross \u0394: Zettai LIVE!!!!!!", "Macross Delta: Zettai LIVE!!!!!!"], "songArtist": "Walk\u00fcre", "songArranger": "Mitsunori Ikeda", "songComposer": "Koichi Kawashima, Mitsunori Ikeda, Junko Zushi", "songName": "Zettai Reido \u03b8 Novatic", "songType": 1, "songTypeNumber": 2, "songDifficulty": 43, "animeType": "TV", "animeVintage": "Spring 2016", "annId": 15555, "malId": 28013, "kitsuId": 9992, "aniListId": 20680, "animeTags": [], "animeGenre": [], "rebroadcast": false, "dub": false, "startPoint": 87.86453103061001, "annSongId": 15555, "length": 89.208, "audio": "t2m8p4.mp3", "video480": "", "video720": "p91l58.webm", "correctGuess": null, "incorrectGuess": null, "sampleWeights": [1, 0, 0, 0, 0, 1, 0, 0, 0, 0, 1, 1], "D": 0.5857864376269049}, {"X": 0, "ST": 2, "STN": 1, "ID": "``14839", "SN": "`MIRAI`", "EN": "Gunslinger Stratos: The Animation", "SA": "GARNiDELiA", "AID": 16632, "animeRomajiName": "Gunslinger Stratos: The Animation", "animeEnglishName": "Gunslinger Stratos: The Animation", "altAnimeNames": ["Gunslinger Stratos: The Animation", "Gunslinger Stratos: The Animation"], "altAnimeNamesAnswers": [], "songArtist": "GARNiDELiA", "songArranger": "GARNiDELiA", "songComposer": "toku", "songName": "MIRAI", "songType": 2, "songTypeNumber": 1, "songDifficulty": 25, "animeType": "TV", "animeVintage": "Spring 2015", "annId": 14839, "malId": 28791, "kitsuId": 10062, "aniListId": 20979, "animeTags": [], "animeGenre": [], "rebroadcast": false, "dub": false, "startPoint": 7.445037250628079, "annSongId": 14839, "length": 88.68, "audio": "j90y18.mp3", "video480": "", "video720": "rgop4k.webm", "correctGuess": null, "incorrectGuess": null, "sampleWeights": [0, 0, 1, 1, 0, 2, 0, 0, 0, 0, 1, 1], "D": 4.0}, {"X": 0, "ST": 2, "STN": 1, "ID": "``45421", "SN": "`Doukashiteru`", "EN": "Dandadan", "SA": "WurtS", "AID": 34211, "animeRomajiName": "Dandadan", "animeEnglishName": "Dandadan", "altAnimeNames": ["Dandadan", "Dandadan"], "altAnimeNamesAnswers": [], "songArtist": "WurtS", "songArranger": "WurtS & Singo Kubota [Jazzin'park]", "songComposer": "WurtS", "songName": "Doukashiteru", "songType": 2, "songTypeNumber": 1, "songDifficulty": 55, "animeType": "TV", "animeVintage": "Summer 2025", "annId": 45421, "malId": 60543, "kitsuId": 49425, "aniListId": 185660, "animeTags": [], "animeGenre": [], "rebroadcast": false, "dub": false, "startPoint": 42.457548686180274, "annSongId": 45421, "length": 87.713, "audio": "slau473mjb2qydr1.mp3", "video480": "", "video720": "b91w4bthtgceiegk.webm", "correctGuess": null, "incorrectGuess": null, "sampleWeights": [0, 0, 0, 0, 0, 0, 0, 0, 0, 0, 1, 0], "D": 1.0}, {"X": 0, "ST": 1, "STN": 1, "ID": "``14461", "SN": "`HEADHUNT`", "EN": "Durarara!! \u00d72 The First Arc", "SA": "OKAMOTO'S", "AID": 16183, "animeRomajiName": "Durarara!!\u00d72 Shou", "animeEnglishName": "Durarara!! \u00d72 The First Arc", "altAnimeNames": ["Durarara!!\u00d72 Shou", "Durarara!! \u00d72 The First Arc"], "altAnimeNamesAnswers": [], "songArtist": "OKAMOTO'S", "songArranger": "OKAMOTO'S & Tomohiro Okubo", "songComposer": "Kouki Okamoto", "songName": "HEADHUNT", "songType": 1, "songTypeNumber": 1, "songDifficulty": 43, "animeType": "TV", "animeVintage": "Winter 2015", "annId": 14461, "malId": 23199, "kitsuId": 8314, "aniListId": 20652, "animeTags": [], "animeGenre": [], "rebroadcast": false, "dub": false, "startPoint": 8.29135855591565, "annSongId": 14461, "length": 88.678, "audio": "smojbq.mp3", "video480": "", "video720": "lu0r5o.webm", "correctGuess": null, "incorrectGuess": null, "sampleWeights": [0, 1, 1, 1, 0, 2, 1, 2, 1, 2, 2, 1], "D": 6.071096851712648}, {"X": 0, "ST": 2, "STN": 1, "ID": "``16126", "SN": "`Bokura no Frontier`", "EN": "Scorching Ping Pong Girls", "SA": "Wake Up, Girls!", "AID": 18557, "animeRomajiName": "Shakunetsu no Takkyuu Musume", "animeEnglishName": "Scorching Ping Pong Girls", "altAnimeNames": ["Shakunetsu no Takkyuu Musume", "Scorching Ping Pong Girls"], "altAnimeNamesAnswers": [], "songArtist": "Wake Up, Girls!", "songArranger": "Keiichi Hirokawa", "songComposer": "Keiichi Hirokawa", "songName": "Bokura no Frontier", "songType": 2, "songTypeNumber": 1, "songDifficulty": 22, "animeType": "TV", "animeVintage": "Fall 2016", "annId": 16126, "malId": 33031, "kitsuId": 12009, "aniListId": 21715, "animeTags": [], "animeGenre": [], "rebroadcast": false, "dub": false, "startPoint": 28.119438740885663, "annSongId": 16126, "length": 89.04, "audio": "lvgoer.mp3", "video480": "els1v1.webm", "video720": "lpe408.webm", "correctGuess": null, "incorrectGuess": null, "sampleWeights": [1, 0, 1, 1, 1, 0, 1, 3, 1, 2, 2, 0], "D": 1.0}, {"X": 0, "ST": 3, "STN": null, "ID": "``31640", "SN": "`Solitude Rain`", "EN": "Love Live! Nijigasaki High School Idol Club", "SA": "Kaori Maeda", "AID": 22934, "animeRomajiName": "Love Live! School Idol Project Nijigasaki Gakuen School Idol Doukoukai", "animeEnglishName": "Love Live! Nijigasaki High School Idol Club", "altAnimeNames": ["Love Live! School Idol Project Nijigasaki Gakuen School Idol Doukoukai", "Love Live! Nijigasaki High School Idol Club"], "altAnimeNamesAnswers": [], "songArtist": "Kaori Maeda", "songArranger": "JOE", "songComposer": "JOE & ERECA", "songName": "Solitude Rain", "songType": 3, "songTypeNumber": null, "songDifficulty": 36, "animeType": "TV", "animeVintage": "Fall 2020", "annId": 31640, "malId": 40879, "kitsuId": 42872, "aniListId": 113970, "animeTags": [], "animeGenre": [], "rebroadcast": false, "dub": false, "startPoint": 79.28604768625175, "annSongId": 31640, "length": 94.031, "audio": "d8crpn.mp3", "video480": "", "video720": "jghixa.webm", "correctGuess": null, "incorrectGuess": null, "sampleWeights": [0, 3, 2, 1, 1, 1, 1, 2, 2, 0, 2, 1, 2], "D": 5.965535159826573}, {"X": 0, "ST": 2, "STN": 1, "ID": "``36409", "SN": "`Bokura ga Oroka da Nante Dare ga Itta`", "EN": "Skeleton Knight in Another World", "SA": "DIALOGUE+", "AID": 24313, "animeRomajiName": "Gaikotsu Kishi-sama, Tadaima Isekai e Odekakechuu", "animeEnglishName": "Skeleton Knight in Another World", "altAnimeNames": ["Gaikotsu Kishi-sama, Tadaima Isekai e Odekakechuu", "Skeleton Knight in Another World"], "altAnimeNamesAnswers": [], "songArtist": "DIALOGUE+", "songArranger": "kz", "songComposer": "Tomoya Tabuchi", "songName": "Bokura ga Oroka da Nante Dare ga Itta", "songType": 2, "songTypeNumber": 1, "songDifficulty": 36, "animeType": "TV", "animeVintage": "Spring 2022", "annId": 36409, "malId": 48760, "kitsuId": 44423, "aniListId": 132474, "animeTags": [], "animeGenre": [], "rebroadcast": false, "dub": false, "startPoint": 51.322596498504964, "annSongId": 36409, "length": 89.28, "audio": "vxcz6h.mp3", "video480": "", "video720": "bncc2g.webm", "correctGuess": null, "incorrectGuess": null, "sampleWeights": [1, 0, 0, 0, 0, 1, 0, 0, 0, 1, 1, 1], "D": 3.267949192431123}, {"X": 0, "ST": 3, "STN": null, "ID": "``15715", "SN": "`Yume de Yozora o Terashitai`", "EN": "Love Live! Sunshine!!", "SA": "Anju Inami, Rikako Aida, Shuka Saitou, Aika Kobayashi, Kanako Takatsuki, Ai Furihata", "AID": 17985, "animeRomajiName": "Love Live! School Idol Project Sunshine!!", "animeEnglishName": "Love Live! Sunshine!!", "altAnimeNames": ["Love Live! School Idol Project Sunshine!!", "Love Live! Sunshine!!"], "altAnimeNamesAnswers": [], "songArtist": "Anju Inami, Rikako Aida, Shuka Saitou, Aika Kobayashi, Kanako Takatsuki, Ai Furihata", "songArranger": "EFFY", "songComposer": "Hajime Mitsumasu", "songName": "Yume de Yozora o Terashitai", "songType": 3, "songTypeNumber": null, "songDifficulty": 37, "animeType": "TV", "animeVintage": "Summer 2016", "annId": 15715, "malId": 32526, "kitsuId": 11745, "aniListId": 21584, "animeTags": [], "animeGenre": [], "rebroadcast": false, "dub": false, "startPoint": 0, "annSongId": 15715, "length": 146.04, "audio": "h22vr4.mp3", "video480": "", "video720": "75pr24.webm", "correctGuess": null, "incorrectGuess": null, "sampleWeights": [0, 0, 0, 0, 1, 0, 0, 0, 0, 0, 0, 1, 0, 0, 0, 0, 0, 0, 0, 0], "D": 0.5857864376269049}, {"X": 0, "ST": 3, "STN": null, "ID": "``17915", "SN": "`is`", "EN": "Terror in Resonance", "SA": "POP ETC", "AID": 15974, "animeRomajiName": "Zankyou no Terror", "animeEnglishName": "Terror in Resonance", "altAnimeNames": ["Zankyou no Terror", "Terror in Resonance"], "altAnimeNamesAnswers": [], "songArtist": "POP ETC", "songArranger": "Yoko Kanno", "songComposer": "Yoko Kanno", "songName": "is", "songType": 3, "songTypeNumber": null, "songDifficulty": 37, "animeType": "TV", "animeVintage": "Summer 2014", "annId": 17915, "malId": 23283, "kitsuId": 8342, "aniListId": 20661, "animeTags": [], "animeGenre": [], "rebroadcast": false, "dub": false, "startPoint": 12.765992807046045, "annSongId": 17915, "length": 84.456, "audio": "l5mhqx.mp3", "video480": "lpf6as.webm", "video720": "yswhuw.webm", "correctGuess": null, "incorrectGuess": null, "sampleWeights": [1, 1, 0, 1, 0, 0, 1, 0, 0, 1, 1, 1], "D": 2.3265063108771393}, {"X": 0, "ST": 3, "STN": null, "ID": "``47814", "SN": "`Many Stories`", "EN": "Beastars Final Season", "SA": "Chica", "AID": 26301, "animeRomajiName": "Beastars Final Season", "animeEnglishName": "Beastars Final Season", "altAnimeNames": ["Beastars Final Season", "Beastars Final Season"], "altAnimeNamesAnswers": ["Beastars"], "songArtist": "Chica", "songArranger": "Satoru Kosaki", "songComposer": "Satoru Kosaki", "songName": "Many Stories", "songType": 3, "songTypeNumber": null, "songDifficulty": 29, "animeType": "ONA", "animeVintage": "Fall 2024", "annId": 47814, "malId": 49469, "kitsuId": 44914, "aniListId": 136880, "animeTags": [], "animeGenre": [], "rebroadcast": false, "dub": false, "startPoint": 3.886633846389665, "annSongId": 47814, "length": 102.985, "audio": "", "video480": "", "video720": "r8avwk.webm", "correctGuess": null, "incorrectGuess": null, "sampleWeights": [1, 0, 0, 2, 0, 1, 0, 0, 0, 0, 1, 0, 1, 0], "D": 3.585786437626905}, {"X": 0, "ST": 1, "STN": 2, "ID": "``11213", "SN": "`Hyadain no Joujou Yuujou`", "EN": "Nichijou: My Ordinary Life", "SA": "Hyadain", "AID": 12142, "animeRomajiName": "Nichijou", "animeEnglishName": "Nichijou: My Ordinary Life", "altAnimeNames": ["Nichijou", "Nichijou: My Ordinary Life"], "altAnimeNamesAnswers": [], "songArtist": "Hyadain", "songArranger": "Kenichi Maeyamada", "songComposer": "Kenichi Maeyamada", "songName": "Hyadain no Joujou Yuujou", "songType": 1, "songTypeNumber": 2, "songDifficulty": 70, "animeType": "TV", "animeVintage": "Spring 2011", "annId": 11213, "malId": 10165, "kitsuId": 6062, "aniListId": 10165, "animeTags": [], "animeGenre": [], "rebroadcast": false, "dub": false, "startPoint": 83.93043351209141, "annSongId": 11213, "length": 88.488, "audio": "6txfb7.mp3", "video480": "pi7xf9.webm", "video720": "cx0gjs.webm", "correctGuess": null, "incorrectGuess": null, "sampleWeights": [0, 0, 0, 0, 0, 0, 0, 1, 0, 0, 0, 0], "D": 1.0}, {"X": 0, "ST": 2, "STN": 1, "ID": "``11929", "SN": "`Vidro Moyou`", "EN": "Waiting in the Summer", "SA": "Nagi Yanagi", "AID": 13448, "animeRomajiName": "Ano Natsu de Matteru", "animeEnglishName": "Waiting in the Summer", "altAnimeNames": ["Ano Natsu de Matteru", "Waiting in the Summer"], "altAnimeNamesAnswers": [], "songArtist": "Nagi Yanagi", "songArranger": "Tomoyuki Nakazawa & Takeshi Ozaki", "songComposer": "Tomoyuki Nakazawa", "songName": "Vidro Moyou", "songType": 2, "songTypeNumber": 1, "songDifficulty": 33, "animeType": "TV", "animeVintage": "Winter 2012", "annId": 11929, "malId": 11433, "kitsuId": 6508, "aniListId": 11433, "animeTags": [], "animeGenre": [], "rebroadcast": false, "dub": false, "startPoint": 95.94283054663813, "annSongId": 11929, "length": 89.472, "audio": "7nt62s.mp3", "video480": "uwgubo.webm", "video720": "7jijlh.webm", "correctGuess": null, "incorrectGuess": null, "sampleWeights": [0, 0, 0, 0, 2, 0, 1, 0, 1, 0, 1, 1], "D": 2.202047647722101}]